MANIFEST.in
README.rst
setup.cfg
setup.py
safeid/__init__.py
safeid/common.py
safeid/httpJson.py
safeid/safeid.py
safeid.egg-info/PKG-INFO
safeid.egg-info/SOURCES.txt
safeid.egg-info/dependency_links.txt
safeid.egg-info/entry_points.txt
safeid.egg-info/not-zip-safe
safeid.egg-info/requires.txt
safeid.egg-info/top_level.txt