Metadata-Version: 1.1
Name: safeid
Version: 1.4
Summary: SafeID is a proof-of-concept web server library that protects user passwords using the Pythia protocol. Web servers can interact with a Pythia server to encrypt new passwords and verify existing passwords.
Home-page: https://github.com/ace0/pyrelic
Author: Adam Everspaugh
Author-email: ace@cs.wisc.edu
License: MIT
Keywords: password encryption authentication
Platform: UNKNOWN
Classifier: Development Status :: 4 - Beta
Classifier: Intended Audience :: Developers
Classifier: Intended Audience :: Information Technology
Classifier: License :: OSI Approved :: MIT License
Classifier: Operating System :: MacOS
Classifier: Operating System :: MacOS :: MacOS X
Classifier: Operating System :: POSIX :: Linux
Classifier: Operating System :: Unix
Classifier: Programming Language :: Python :: 2
Classifier: Programming Language :: Python :: 2.7
Classifier: Topic :: Security
Classifier: Topic :: Security :: Cryptography
Classifier: Topic :: System :: Systems Administration :: Authentication/Directory
